em_simulation/__init__.py
em_simulation/create_gpr_image.py
em_simulation/global_constants.py
em_simulation/main_example.py
em_simulation/object_creation.py
em_simulation/propagator_2D.py
em_simulation/user_messages.py
em_simulation/visualization.py
em_simulation/waveform.py
em_simulation-0.8.3.dist-info/LICENSE
em_simulation-0.8.3.dist-info/METADATA
em_simulation-0.8.3.dist-info/WHEEL
em_simulation-0.8.3.dist-info/top_level.txt
em_simulation-0.8.3.dist-info/RECORD
