Metadata-Version: 2.1
Name: em_simulation
Version: 0.8.3
Summary: 2D Electromagnetic Simulator for GPR Scenarios
Home-page: https://github.com/aplatag/project_em_simulation_2D.git
Author: Aplatag
License: MIT
License-File: LICENSE
Requires-Dist: numpy
